{
   "endpoints": [
      {
         "method": "POST",
         "url": "https://www.google.com/",
         "headers": [
            {
               "name": "Cookie",
               "value": "token=DEADCAFE"
            }
         ],
         "body": "hello"
      },
      {
         "url": "https://reqbin.com/post-online"
      },
      {
         "url": "https://news.ycombinator.com"
      },
      {
         "url": "www.baddomain1111.com"
      }
   ],
   "num_requests": 3,
   "retry_failed": true
}